commonmark_extensions/__init__.py
commonmark_extensions/make_reference_output.py
commonmark_extensions/plaintext.py
commonmark_extensions/tables.py
commonmark_extensions/tests.py
commonmarkextensions-0.0.6.dist-info/LICENSE
commonmarkextensions-0.0.6.dist-info/METADATA
commonmarkextensions-0.0.6.dist-info/WHEEL
commonmarkextensions-0.0.6.dist-info/entry_points.txt
commonmarkextensions-0.0.6.dist-info/top_level.txt
commonmarkextensions-0.0.6.dist-info/RECORD
