Metadata-Version: 2.1
Name: commonmarkextensions
Version: 0.0.6
Summary: Tables and plain text rendering extension to commonmark.
Home-page: https://github.com/GovReady/CommonMark-py-Extensions
Author: GovReady PBC
Author-email: 
License: BSD 3
Keywords: markdown commonmark tables plaintext
Platform: UNKNOWN
Classifier: Intended Audience :: Developers
Classifier: Topic :: Software Development :: Libraries :: Python Modules
Classifier: Programming Language :: Python :: 2
Classifier: Programming Language :: Python :: 2.7
Classifier: Programming Language :: Python :: 3
Classifier: Programming Language :: Python :: 3.4
Classifier: Programming Language :: Python :: 3.5
Classifier: Programming Language :: Python :: 3.6
Classifier: Programming Language :: Python :: 3.7
Classifier: Programming Language :: Python :: 3.8
Classifier: Programming Language :: Python :: 3.9
Requires-Dist: commonmark (<=0.9.1,>=0.8.0)
